tsp_solvers/__init__.py
tsp_solvers/graph/__init__.py
tsp_solvers/graph/graph.py
tsp_solvers/initializers/__init__.py
tsp_solvers/initializers/nearest_neighbor.py
tsp_solvers/initializers/random.py
tsp_solvers/methods/__init__.py
tsp_solvers/methods/aco.py
tsp_solvers/methods/base.py
tsp_solvers/methods/christofides.py
tsp_solvers/methods/ga.py
tsp_solvers/methods/lp.py
tsp_solvers/methods/pso.py
tsp_solvers/methods/sa.py
tsp_solvers/methods/two_opt.py
tsp_solvers/tests/__init__.py
tsp_solvers/tests/const.py
tsp_solvers/tests/test_ga.py
tsp_solvers-0.0.13.dist-info/LICENSE
tsp_solvers-0.0.13.dist-info/METADATA
tsp_solvers-0.0.13.dist-info/WHEEL
tsp_solvers-0.0.13.dist-info/top_level.txt
tsp_solvers-0.0.13.dist-info/RECORD
